timer.sv
module timer #(
  parameter WIDTH = 32         // ширина таймера в битах, по умолчанию 32
) (
  input wire clk,              // сигнал тактового сигнала
  input wire reset_n,          // сигнал асинхронного сброса по негативному фронту
  input wire[3:0] ocp_mcmd,    // сигнал команды для OCP PIO
  input wire [31:0] ocp_maddr, // адрес для OCP PIO
  input wire [31:0] ocp_data,  // данные для чтения/записи
  output reg [31:0] ocp_sdata, // данные для ответа по OCP PIO
  output reg ocp_sresp,        // сигнал ответа по OCP PIO
  output reg _scmdaccept       // сигнал подтверждения по OCP PIO
);

  // Параметры адресного пространства 
  parameter TIMER_START_ADDR = 32'h40000000; // адрес стартового значения таймера
  parameter TIMER_CURR_ADDR  = 32'h40000004; // адрес текущего значения таймера
  parameter TIMER_CTRL_ADDR  = 32'h40000008; // адрес регистра старт-стоп таймера

  // Локальные переменные
  reg [WIDTH-1:0] start_val;   // начальное значение таймера
  reg [WIDTH-1:0] cur_val;     // текущее значение таймера
  reg active;                  // флаг активности таймера
  reg busy;                    // флаг занятости таймера

  // Параметры записи и чтения
  parameter WRITE = 3'b100;   // параметр записи WRITE
  parameter READ = 3'b010;    // параметр чтения READ

  always @(posedge clk) begin
    // присутствует отрицательный фронт сигнала сброса
    if (!reset_n) begin
      start_val <= 0;          // сбрасываем начальное значение таймера
      cur_val <= 0;            // сбрасываем текущее значение таймера
      active <= 0;             // сбрасываем флаг активности таймера
      ocp_sdata <= 0;          // сбрасываем данные ответа таймера
      busy <= 0;               // сбрасывыаем флаг занятости таймера
    end
    // Декремент таймера при активном состоянии
    if (active && cur_val != 0) begin
      cur_val <= cur_val - 1;
    end
    // Установка стартового значения таймера, если текущее значение равно 0 и таймер активен
    if (active && cur_val == 0) begin
      cur_val <= start_val;
    end
  end

  always @(posedge ocp_maddr, ocp_mcmd) begin
    // Чтение/запись регистров через интерфейс OCP PIO
    ocp_sresp <= 0;              // операции ещё нету -> сигнал ответа 0
    _scmdaccept <= 0;            // операции ещё нету -> сигнал подтверждения 0

    // если операция уже выполняется
    if (busy) begin
      // Отклоняем операции, если интерфейс занят
      ocp_sresp <= 1'b0;
      _scmdaccept <= 1'b0;
    end
    
    else begin
    busy <= 1'b1;                         // интерфейс занят
    // проверяем команду на обращение к регистрам
    case (ocp_maddr)
      // обращение к регистру start_val
      TIMER_START_ADDR: begin
        if (ocp_mcmd == READ) begin       // чтение данных в регистре
          ocp_sdata <= start_val;
        end
        else if (ocp_mcmd == WRITE) begin // запись данных в регистр start_val 
          start_val <= ocp_data;
        end
        // операция выполнена. Устанавливаем сигналы подтверждения операции
        ocp_sresp <= 1;
        _scmdaccept <= 1;
      end

      // обращение к регистру cur_val
      TIMER_CURR_ADDR: begin
        if (ocp_mcmd == READ) begin        // чтение данных из регистра текущего знаения cur_val
          if (active == 0) begin           // чтение разрешено только в остановленном состоянии
            ocp_sdata <= cur_val;          // читаем данные
          end
          // иначе, если таймер не остановлен - записываем 0
          else begin
            ocp_sdata <= 0;
          end
        end
        // операция выполнена. Устанавливаем сигналы подтверждения операции
        ocp_sresp <= 1;
        _scmdaccept <= 1;
      end

      // обращение к регистру active
      TIMER_CTRL_ADDR: begin
      // читаем значение регистра
      if (ocp_mcmd == READ) begin          // чтение данных из регистра активности active
        ocp_sdata <= active;               // чтение данных об активности таймера
        // операция выполнена. Устанавливаем сигналы подтверждения операции
        ocp_sresp <= 1;
        _scmdaccept <= 1;
      end
      //записать значения в регистр
      else if (ocp_mcmd == WRITE) begin          // запись значения флага активности таймера 
        if (ocp_data == 1 && active == 0) begin  // Таймер был выключен и пришло значение 1. Включение таймера
          active <= 1;                           // устанавливаем флаг активности таймера
          cur_val <= start_val;                  // устанавливаем значение отсчёта таймера для начала работы
          // операция выполнена. Устанавливаем сигналы подтверждения операции
          ocp_sresp <= 1;
          _scmdaccept <= 1;
        end
        // таймер активен и пришел флаг сброса активности
        else if (ocp_data == 0 && active == 1) begin        // выключение таймера
          active <= 0;                                       // убираем флаг активности таймера
          // операция выполнена. Устанавливаем сигналы подтверждения операции
          ocp_sresp <= 1;
          _scmdaccept <= 1;
        end 
        // таймер активен и пришел флаг установки активности
        else if (ocp_data == 1 && active == 1) begin        // состояние таймера не изменится
          active <= 1;                                      // устанавливаем флаг активности таймера
          // операция выполнена. Устанавливаем сигналы подтверждения операции
          ocp_sresp <= 1;
          _scmdaccept <= 1;
        end
        // таймер неактивен и пришел флаг сброса активности
        else if (ocp_data == 0 && active == 0) begin        // состояние таймера не изменится
          active <= 0;                                      // сбрасываем флаг активности таймера
          // операция выполнена. Устанавливаем сигналы подтверждения операции
          ocp_sresp <= 1;
          _scmdaccept <= 1;
        end
        // непредусмотренное состояние - операция не выполнена
        else  begin
          ocp_sresp <= 0;
          _scmdaccept <= 0;
        end
      end
    end
    // попали не в тот регитср - операция не выполнена. Флаги подтверждения 0
    default: begin
        ocp_sresp <= 0;
        _scmdaccept <= 0;
    end
    endcase
    end;
  end

  // Логика сброса флага занятости интерфейса
  // если таймер не занят, т.е флаг подтверждения новой операции 0
  always @(negedge ocp_sresp) begin
      // сбрасываем флаг занятости
      busy <= 1'b0;
  end
endmodule

timer_tb.sv
`include "timer.sv"                    // директива препроцессора, которая включает файл timer.v в текущий код.
module timer_tb;
  // Параметры симуляции
  parameter WIDTH = 32;
  parameter WRITE = 3'b100;   // Параметр записи WRITE
  parameter READ = 3'b010;    // Параметр чтения READ
  
  // Сигналы модуля
  reg clk;                              // сигнал тактового сигнала 
  reg reset;                            // сигнал асинхронного сброса
  reg [3:0] ocp_mcmd;                   // сигнал команды для OCP PIO
  reg [WIDTH-1:0] ocp_maddr;            // адрес для OCP PIO
  reg [WIDTH-1:0] ocp_data;             // данные для чтения/записи
  wire [WIDTH-1:0] ocp_sdata;           // данные для ответа по OCP PIO
  wire ocp_sresp;                       // сигнал ответа по OCP PIO
  wire _scmdaccept;                     // сигнал подтверждения по OCP PIO
  
  // Подключение модуля
  timer #(.WIDTH(WIDTH))
dut (
    .clk          (clk),
    .reset_n      (reset),
    .ocp_mcmd     (ocp_mcmd),
    .ocp_maddr    (ocp_maddr),
    .ocp_data     (ocp_data),
    .ocp_sdata    (ocp_sdata),
    .ocp_sresp    (ocp_sresp),
    ._scmdaccept  (_scmdaccept)
  );
  

// Определение task-ов для проверки регистров

// запись в регистр начального значения
task test_write_start (input logic [WIDTH-1:0] start_value);
    ocp_mcmd = WRITE;             // запись в регистр START
    ocp_maddr = 32'h40000000;     // адрес регистра START
    ocp_data = start_value;       // данные для записи
    @(posedge clk);
    ocp_mcmd = 3'b0;              // обнуляем сигнал команды
    @(posedge clk);
endtask


// чтение из регистра начального значения
task test_read_start(input logic [WIDTH-1:0] start_value);
    ocp_mcmd = READ;              // чтение из регистра START
    ocp_maddr = 32'h40000000;     // адрес регистра START
    @(posedge clk);
    $display("ocp_sdata = %d", ocp_sdata);
    $display("ocp_sresp = %d", ocp_sresp);
    // проверка на чтение записанного в START значения
    if (ocp_sresp !== 1 || ocp_sdata !== start_value) begin
      $display("FAILED in writing START");
    end
    else begin
      $display("WRITING in START COMPLETED");
    end
    ocp_mcmd = 3'b0;              // обнуляем сигнал команды
    @(posedge clk);
endtask


// чтение текущего значения таймера
task test_read_curr;
    ocp_mcmd = READ;              // чтение из регистра CURR
    ocp_maddr = 32'h40000004;     // адрес регистра CURR
    @(posedge clk);
    $display("ocp_sdata = %d", ocp_sdata);
    $display("ocp_sresp = %d", ocp_sresp);
    ocp_mcmd = 3'b0;              // обнуляем сигнал команды
    @(posedge clk);
endtask
  

// остановка таймера
task test_write_ctrl_stop;
    ocp_mcmd = WRITE;             // запись в регистр CTRL
    ocp_maddr = 32'h40000008;     // адрес регистра CTRL
    ocp_data = 0;                 // флаг остановки таймера
    @(posedge clk);
    ocp_mcmd = 3'b0;              // обнуляем сигнал команды
    @(posedge clk);
endtask
  

// запуск таймера
task test_write_ctrl_start;
    ocp_mcmd = WRITE;             // запись в регистр CTRL
    ocp_maddr = 32'h40000008;     // адрес регистра CTRL
    ocp_data = 1;                 // флаг запуска таймера
    @(posedge clk);
    ocp_mcmd = 3'b0;              // обнуляем сигнал команды
    @(posedge clk);
endtask


// чтение текущего состояния таймера (запущен или остановлен)
task test_read_ctrl;
    ocp_mcmd = READ;              // чтение из регистра CTRL
    ocp_maddr = 32'h40000008;     // адрес регистра CTRL
    @(posedge clk);
    $display("ocp_sdata = %d", ocp_sdata);
    $display("ocp_sresp = %d", ocp_sresp);
    // проверка на то активен ли таймер
    if (ocp_sresp !== 1 || ocp_sdata !== 1) begin
      $display("Timer is not active");
    end
    ocp_mcmd = 3'b0;              // обнуляем сигнал команды
    @(posedge clk);
endtask


// сброс таймера активен
task test_reset_timer_on;
    reset = 0;                    // сбрасываем значения таймера - таймер отключается и обнуляется
    @(posedge clk); 
endtask


// убираем сброс таймера
task test_reset_timer_off;
    reset = 1;                    // убираем сброс таймера
    @(posedge clk);
endtask


  // Тесты
  initial begin
    // начальные значения
    reset = 1;
    clk = 0;
    ocp_mcmd = 0;
    ocp_maddr = 0;
    ocp_data = 0;
    // Начальный сброс таймера
    @(posedge clk);
    test_reset_timer_on;
    @(posedge clk);
    // Убираем сброс таймера
    test_reset_timer_off;
    @(posedge clk);
    

    // Тест 1: проверка чтения и записи регистра START
    $display("\n\t\t\t TEST 1");
    test_write_start(50);              // записываем в таймер число 50
    test_read_start(50);               // сравниваем прочитанное число из регистра START с записанной 50-кой


    // Тест 2: проверка чтения регистра CURR в рабочем состоянии. Должно прочитаться 0
    $display("\n\t\t\t TEST 2");
    test_write_start(10);              // записываем в таймер число 10
    test_write_ctrl_start;             // запускаем таймер. active -> 1
    $display("       1          ");
    test_read_ctrl;                    // проверка на выставление в active значения 1
    // проверка на то, что таймер не может читать в остановленном состоянии
    // active = 1 -> ничего не можем прочитать
    // сработает условие else begin ocp_sdata <= 0;
    $display("       2          ");
    test_read_curr;
    // штабель проверок, что мы не можем получить текущее значение таймера, пока active = 1
    if (ocp_sresp !== 1 || ocp_sdata !== 10) begin
      $display("TEST 2 COMPLETED at 10");
    end
    @(posedge clk);
    if (ocp_sresp !== 1 || ocp_sdata !== 9) begin
      $display("TEST 2 COMPLETED at 9");
    end
    @(posedge clk);
    if (ocp_sresp !== 1 || ocp_sdata !== 8) begin
      $display("TEST 2 COMPLETED at 8");
    end


    // Тест 3: проверка чтения регистра CURR в остановленном состоянии
    $display("\n\t\t\t TEST 3");
    test_write_ctrl_stop;               // останавливаем таймер. Устанавливаем active -> 0
    test_read_curr;                     // читаем регистр CURR. Таймер остановлен. Это можно сделать
    // проверяем, что прочитали не 0, как это было бы при active = 1
    if (ocp_sresp !== 1 || ocp_sdata !== 0) begin
      $display("TEST 3 COMPLETED");
    end


    // Тест 4: проверка чтения CURR при запуске и остановке таймера
    $display("\n\t\t\t TEST 4");
    test_write_ctrl_start;               // запускаем таймер. Устанавливаем active -> 1
    $display("       1          ");
    test_read_ctrl;                      // читаем регистр CTRL. Проверяем, что active = 1
    test_write_ctrl_stop;                // останавливаем таймер. Устанавливаем active -> 0
    $display("       2          ");
    test_read_ctrl;                      // читаем регистр CTRL. Проверяем, что active = 0
    $display("       3          ");
    test_read_curr;                      // читаем регистр CURR. Таймер остановлен. Это можно сделать
    // проверяем, что прочитали не 0, как это было бы при active = 1
    if (ocp_sdata == 0) begin
      $display("TEST 4 FAIL of count");
    end
    else begin
      $display("TEST 4 COMPLETED");
    end
    

    // Тест 5: проверка чтения из CURR для остановленного таймера
    $display("\n\t\t\t TEST 5");
    test_write_ctrl_start;                // запускаем таймер. Устанавливаем active -> 1
    $display("       1          ");
    test_read_ctrl;                       // читаем регистр CTRL. Проверяем, что active = 1
    @(posedge clk);
    test_write_ctrl_stop;                 // останавливаем таймер. Устанавливаем active -> 0
    $display("       2          ");
    test_read_ctrl;                       // читаем регистр CTRL. Проверяем, что active = 0
    $display("       3          ");
    test_read_curr;                       // читаем регистр CURR. Таймер остановлен. Это можно сделать
    // проверяем, что прочитали из таймера нужное число
    if (ocp_sdata !== 5) begin
      $display("TEST 5 FAILED at 5");
    end
    else begin
      $display("TEST 5 COMPLETED");
    end
    

    // Тест 6: проверка сброса таймера
    $display("\n\t\t\t TEST 6");
    test_write_ctrl_start;                // запускаем таймер. Устанавливаем active -> 1
    @(posedge clk);
    test_reset_timer_on;                  // сбрасываем таймер. active -> 0; cur_val -> 0; start_val -> 0;
    @(posedge clk);
    @(posedge clk);
    $display("       1          ");
    test_read_curr;
    @(posedge clk);                       // пробуем прочитать текущее значение таймера. cur_val = 0; и таймер неактивен
    // проверка, что прочитали 0
    if (ocp_sdata !== 0) begin
      $display("TEST 6 Failed");
    end
    @(posedge clk);
    $display("       2          ");
    test_read_ctrl;                        // читаем регистр CTRL. Проверяем, что active при сбросе = 0  
    @(posedge clk);
    test_reset_timer_off;                  // убираем сброс таймера


     // Тест 7: проверка отсчёта таймера до конца
    test_write_start(10);              // записываем в таймер число 10
    test_write_ctrl_start;             // запускаем таймер. active -> 1
    test_read_ctrl;                    // читаем регистр CTRL. Проверяем, что active = 1
    repeat (10) begin
    @(posedge clk);  
    end
    test_write_ctrl_stop;              // останавливаем таймер. Устанавливаем active -> 0
    $display("All tests passed");
    $finish;
  end


  // генерация тактового сигнала
  always #10 clk = ~clk;
  // создание файла .vcd и вывести значения переменных волны для отображения в визуализаторе волн
  initial begin
    $dumpfile("timer.vcd");              // создание файла для сохранения результатов симуляции
    $dumpvars(0, timer_tb);              // установка переменных для сохранения в файле
  end 
endmodule

timer.vcd
$date
	Mon Jun 05 21:05:19 2023
$end
$version
	Icarus Verilog
$end
$timescale
	1s
$end
$scope module timer_tb $end
$var wire 1 ! ocp_sresp $end
$var wire 32 " ocp_sdata [31:0] $end
$var wire 1 # _scmdaccept $end
$var reg 1 $ clk $end
$var reg 32 % ocp_data [31:0] $end
$var reg 32 & ocp_maddr [31:0] $end
$var reg 4 ' ocp_mcmd [3:0] $end
$var reg 1 ( reset $end
$scope module dut $end
$var wire 1 $ clk $end
$var wire 32 ) ocp_data [31:0] $end
$var wire 32 * ocp_maddr [31:0] $end
$var wire 4 + ocp_mcmd [3:0] $end
$var wire 1 ( reset_n $end
$var reg 1 # _scmdaccept $end
$var reg 1 , active $end
$var reg 1 - busy $end
$var reg 32 . cur_val [31:0] $end
$var reg 32 / ocp_sdata [31:0] $end
$var reg 1 ! ocp_sresp $end
$var reg 32 0 start_val [31:0] $end
$upscope $end
$scope task test_read_ctrl $end
$upscope $end
$scope task test_read_curr $end
$upscope $end
$scope task test_read_start $end
$var reg 32 1 start_value [31:0] $end
$upscope $end
$scope task test_reset_timer_off $end
$upscope $end
$scope task test_reset_timer_on $end
$upscope $end
$scope task test_write_ctrl_start $end
$upscope $end
$scope task test_write_ctrl_stop $end
$upscope $end
$scope task test_write_start $end
$var reg 32 2 start_value [31:0] $end
$upscope $end
$upscope $end
$enddefinitions $end
#0
$dumpvars
bx 2
bx 1
bx 0
bx /
bx .
0-
x,
b0 +
b0 *
b0 )
1(
b0 '
b0 &
b0 %
0$
0#
bx "
0!
$end
#10
0(
1$
#20
0$
#30
b0 "
b0 /
0,
b0 .
b0 0
1$
#40
0$
#50
1(
1$
#60
0$
#70
1$
#80
0$
#90
1#
1!
b110010 0
1-
b110010 %
b110010 )
b1000000000000000000000000000000 &
b1000000000000000000000000000000 *
b100 '
b100 +
b110010 2
1$
#100
0$
#110
0-
0#
0!
b0 '
b0 +
1$
#120
0$
#130
1#
1!
b110010 "
b110010 /
1-
b10 '
b10 +
b110010 1
1$
#140
0$
#150
0-
0#
0!
b0 '
b0 +
1$
#160
0$
#170
1#
1!
b1010 0
1-
b1010 %
b1010 )
b100 '
b100 +
b1010 2
1$
#180
0$
#190
0-
0#
0!
b0 '
b0 +
1$
#200
0$
#210
1#
1!
b1010 .
1,
1-
b1 %
b1 )
b1000000000000000000000000001000 &
b1000000000000000000000000001000 *
b100 '
b100 +
1$
#220
0$
#230
0-
0#
0!
b1001 .
b0 '
b0 +
1$
#240
0$
#250
1#
1!
b1 "
b1 /
1-
b1000 .
b10 '
b10 +
1$
#260
0$
#270
0-
0#
0!
b111 .
b0 '
b0 +
1$
#280
0$
#290
1#
1!
b0 "
b0 /
1-
b110 .
b1000000000000000000000000000100 &
b1000000000000000000000000000100 *
b10 '
b10 +
1$
#300
0$
#310
0-
0#
0!
b101 .
b0 '
b0 +
1$
#320
0$
#330
b100 .
1$
#340
0$
#350
b11 .
1$
#360
0$
#370
1#
1!
0,
1-
b10 .
b0 %
b0 )
b1000000000000000000000000001000 &
b1000000000000000000000000001000 *
b100 '
b100 +
1$
#380
0$
#390
0-
0#
0!
b0 '
b0 +
1$
#400
0$
#410
1#
1!
b10 "
b10 /
1-
b1000000000000000000000000000100 &
b1000000000000000000000000000100 *
b10 '
b10 +
1$
#420
0$
#430
0-
0#
0!
b0 '
b0 +
1$
#440
0$
#450
1#
1!
b1010 .
1,
1-
b1 %
b1 )
b1000000000000000000000000001000 &
b1000000000000000000000000001000 *
b100 '
b100 +
1$
#460
0$
#470
0-
0#
0!
b1001 .
b0 '
b0 +
1$
#480
0$
#490
1#
1!
b1 "
b1 /
1-
b1000 .
b10 '
b10 +
1$
#500
0$
#510
0-
0#
0!
b111 .
b0 '
b0 +
1$
#520
0$
#530
1#
1!
0,
1-
b110 .
b0 %
b0 )
b100 '
b100 +
1$
#540
0$
#550
0-
0#
0!
b0 '
b0 +
1$
#560
0$
#570
1#
1!
b0 "
b0 /
1-
b10 '
b10 +
1$
#580
0$
#590
0-
0#
0!
b0 '
b0 +
1$
#600
0$
#610
1#
1!
b110 "
b110 /
1-
b1000000000000000000000000000100 &
b1000000000000000000000000000100 *
b10 '
b10 +
1$
#620
0$
#630
0-
0#
0!
b0 '
b0 +
1$
#640
0$
#650
1#
1!
b1010 .
1,
1-
b1 %
b1 )
b1000000000000000000000000001000 &
b1000000000000000000000000001000 *
b100 '
b100 +
1$
#660
0$
#670
0-
0#
0!
b1001 .
b0 '
b0 +
1$
#680
0$
#690
1#
1!
b1 "
b1 /
1-
b1000 .
b10 '
b10 +
1$
#700
0$
#710
0-
0#
0!
b111 .
b0 '
b0 +
1$
#720
0$
#730
b110 .
1$
#740
0$
#750
1#
1!
0,
1-
b101 .
b0 %
b0 )
b100 '
b100 +
1$
#760
0$
#770
0-
0#
0!
b0 '
b0 +
1$
#780
0$
#790
1#
1!
b0 "
b0 /
1-
b10 '
b10 +
1$
#800
0$
#810
0-
0#
0!
b0 '
b0 +
1$
#820
0$
#830
1#
1!
b101 "
b101 /
1-
b1000000000000000000000000000100 &
b1000000000000000000000000000100 *
b10 '
b10 +
1$
#840
0$
#850
0-
0#
0!
b0 '
b0 +
1$
#860
0$
#870
1#
1!
b1010 .
1,
1-
b1 %
b1 )
b1000000000000000000000000001000 &
b1000000000000000000000000001000 *
b100 '
b100 +
1$
#880
0$
#890
0-
0#
0!
b1001 .
b0 '
b0 +
1$
#900
0$
#910
b1000 .
1$
#920
0$
#930
b111 .
0(
1$
#940
0$
#950
b0 "
b0 /
0,
b110 .
b0 0
1$
#960
0$
#970
b0 .
1$
#980
0$
#990
1#
1!
1-
b1000000000000000000000000000100 &
b1000000000000000000000000000100 *
b10 '
b10 +
1$
#1000
0$
#1010
0#
0!
0-
b0 '
b0 +
1$
#1020
0$
#1030
1$
#1040
0$
#1050
1$
#1060
0$
#1070
1#
1!
1-
b1000000000000000000000000001000 &
b1000000000000000000000000001000 *
b10 '
b10 +
1$
#1080
0$
#1090
0#
0!
0-
b0 '
b0 +
1$
#1100
0$
#1110
1$
#1120
0$
#1130
1(
1$
#1140
0$
#1150
1#
1!
b1010 0
1-
b1010 %
b1010 )
b1000000000000000000000000000000 &
b1000000000000000000000000000000 *
b100 '
b100 +
1$
#1160
0$
#1170
0-
0#
0!
b0 '
b0 +
1$
#1180
0$
#1190
1#
1!
b1010 .
1,
1-
b1 %
b1 )
b1000000000000000000000000001000 &
b1000000000000000000000000001000 *
b100 '
b100 +
1$
#1200
0$
#1210
0-
0#
0!
b1001 .
b0 '
b0 +
1$
#1220
0$
#1230
1#
1!
b1 "
b1 /
1-
b1000 .
b10 '
b10 +
1$
#1240
0$
#1250
0-
0#
0!
b111 .
b0 '
b0 +
1$
#1260
0$
#1270
b110 .
1$
#1280
0$
#1290
b101 .
1$
#1300
0$
#1310
b100 .
1$
#1320
0$
#1330
b11 .
1$
#1340
0$
#1350
b10 .
1$
#1360
0$
#1370
b1 .
1$
#1380
0$
#1390
b0 .
1$
#1400
0$
#1410
b1010 .
1$
#1420
0$
#1430
b1001 .
1$
#1440
0$
#1450
b1000 .
1$
#1460
0$
#1470
1#
1!
0,
1-
b111 .
b0 %
b0 )
b100 '
b100 +
1$
#1480
0$
#1490
0-
0#
0!
b0 '
b0 +
1$
